srilanka_lottery/__init__.py
srilanka_lottery/scraper.py
srilanka_lottery-0.1.1.dist-info/licenses/LICENSE
srilanka_lottery-0.1.1.dist-info/METADATA
srilanka_lottery-0.1.1.dist-info/WHEEL
srilanka_lottery-0.1.1.dist-info/top_level.txt
srilanka_lottery-0.1.1.dist-info/RECORD
