Metadata-Version: 2.4
Name: srilanka_lottery
Version: 0.1.1
Summary: Scrape Sri Lanka lottery results from NLB and DLB websites with this Python package
Home-page: https://github.com/ishanoshada/srilanka-lottery
Author: Ishan Oshada
Author-email: ic31908@gmail.com
Keywords: lottery,Sri Lanka lottery,NLB,DLB,web scraping,lottery results,Python lottery scraper,lottery data,National Lottery Board,Development Lottery Board,lottery API,data extraction
Classifier: Development Status :: 3 - Alpha
Classifier: Intended Audience :: Developers
Classifier: Topic :: Software Development :: Libraries :: Python Modules
Classifier: Topic :: Internet :: WWW/HTTP :: Dynamic Content
Classifier: License :: OSI Approved :: MIT License
Classifier: Programming Language :: Python :: 3
Classifier: Programming Language :: Python :: 3.6
Classifier: Programming Language :: Python :: 3.7
Classifier: Programming Language :: Python :: 3.8
Classifier: Programming Language :: Python :: 3.9
Classifier: Programming Language :: Python :: 3.10
Classifier: Programming Language :: Python :: 3.11
Classifier: Operating System :: OS Independent
License-File: LICENSE
Requires-Dist: requests>=2.28.0
Requires-Dist: beautifulsoup4>=4.11.0
Dynamic: author
Dynamic: author-email
Dynamic: classifier
Dynamic: description
Dynamic: description-content-type
Dynamic: home-page
Dynamic: keywords
Dynamic: license-file
Dynamic: requires-dist
Dynamic: summary
